odoo/addons/mass_mailing_partner/README.rst
odoo/addons/mass_mailing_partner/__init__.py
odoo/addons/mass_mailing_partner/__manifest__.py
odoo/addons/mass_mailing_partner/hooks.py
odoo/addons/mass_mailing_partner/i18n/am.po
odoo/addons/mass_mailing_partner/i18n/ar.po
odoo/addons/mass_mailing_partner/i18n/bg.po
odoo/addons/mass_mailing_partner/i18n/bs.po
odoo/addons/mass_mailing_partner/i18n/ca.po
odoo/addons/mass_mailing_partner/i18n/ca_ES.po
odoo/addons/mass_mailing_partner/i18n/cs.po
odoo/addons/mass_mailing_partner/i18n/da.po
odoo/addons/mass_mailing_partner/i18n/de.po
odoo/addons/mass_mailing_partner/i18n/el_GR.po
odoo/addons/mass_mailing_partner/i18n/en_AU.po
odoo/addons/mass_mailing_partner/i18n/en_GB.po
odoo/addons/mass_mailing_partner/i18n/es.po
odoo/addons/mass_mailing_partner/i18n/es_AR.po
odoo/addons/mass_mailing_partner/i18n/es_CL.po
odoo/addons/mass_mailing_partner/i18n/es_CO.po
odoo/addons/mass_mailing_partner/i18n/es_CR.po
odoo/addons/mass_mailing_partner/i18n/es_DO.po
odoo/addons/mass_mailing_partner/i18n/es_EC.po
odoo/addons/mass_mailing_partner/i18n/es_ES.po
odoo/addons/mass_mailing_partner/i18n/es_MX.po
odoo/addons/mass_mailing_partner/i18n/es_PE.po
odoo/addons/mass_mailing_partner/i18n/es_PY.po
odoo/addons/mass_mailing_partner/i18n/es_VE.po
odoo/addons/mass_mailing_partner/i18n/et.po
odoo/addons/mass_mailing_partner/i18n/eu.po
odoo/addons/mass_mailing_partner/i18n/fa.po
odoo/addons/mass_mailing_partner/i18n/fi.po
odoo/addons/mass_mailing_partner/i18n/fr.po
odoo/addons/mass_mailing_partner/i18n/fr_CA.po
odoo/addons/mass_mailing_partner/i18n/fr_CH.po
odoo/addons/mass_mailing_partner/i18n/fr_FR.po
odoo/addons/mass_mailing_partner/i18n/gl.po
odoo/addons/mass_mailing_partner/i18n/gl_ES.po
odoo/addons/mass_mailing_partner/i18n/he.po
odoo/addons/mass_mailing_partner/i18n/hi.po
odoo/addons/mass_mailing_partner/i18n/hr.po
odoo/addons/mass_mailing_partner/i18n/hr_HR.po
odoo/addons/mass_mailing_partner/i18n/hu.po
odoo/addons/mass_mailing_partner/i18n/id.po
odoo13_addon_mass_mailing_partner-13.0.1.1.2.dist-info/METADATA
odoo13_addon_mass_mailing_partner-13.0.1.1.2.dist-info/WHEEL
odoo13_addon_mass_mailing_partner-13.0.1.1.2.dist-info/top_level.txt
odoo13_addon_mass_mailing_partner-13.0.1.1.2.dist-info/RECORD
